pie/__init__.py
pie/commit_build.py
pie/constants.py
pie/default_settings.json
pie/initialization.py
pie/optimize.py
pie/pretrain_encoder.py
pie/settings.py
pie/tagger.py
pie/torch_utils.py
pie/trainer.py
pie/utils.py
pie/data/__init__.py
pie/data/base_reader.py
pie/data/conll_reader.py
pie/data/dataset.py
pie/data/reader.py
pie/data/tabreader.py
pie/data/tei_reader.py
pie/data/preprocessors/__init__.py
pie/data/preprocessors/edit_tree_tuples.py
pie/data/preprocessors/edit_trees.py
pie/data/preprocessors/greedy_scripts.py
pie/models/__init__.py
pie/models/attention.py
pie/models/base_model.py
pie/models/beam_search.py
pie/models/decoder.py
pie/models/embedding.py
pie/models/encoder.py
pie/models/highway.py
pie/models/loaders.py
pie/models/lstm.py
pie/models/model.py
pie/models/scorer.py
pie/scripts/__init__.py
pie/scripts/evaluate.py
pie/scripts/group.py
pie/scripts/inspect_model.py
pie/scripts/tag.py
pie/scripts/tag_pipe.py
pie/scripts/train.py
pie/webapp/__init__.py
test/__init__.py
test/data/__init__.py
test/data/test_data.py
test/data/test_tabreader.py
nlp_pie-0.3.8.dist-info/LICENSE
nlp_pie-0.3.8.dist-info/METADATA
nlp_pie-0.3.8.dist-info/WHEEL
nlp_pie-0.3.8.dist-info/entry_points.txt
nlp_pie-0.3.8.dist-info/top_level.txt
nlp_pie-0.3.8.dist-info/RECORD
