Metadata-Version: 2.1
Name: nlp-pie
Version: 0.3.8
Summary: A Framework for Joint Learning of Sequence Labeling Tasks
Home-page: https://github.com/emanjavacas/pie
Author: Enrique Manjavacas; Mike Kestemont; Thibault Clerice
License: MIT
Platform: UNKNOWN
Classifier: License :: OSI Approved :: MIT License
Classifier: Programming Language :: Python
Classifier: Programming Language :: Python :: 3
Classifier: Programming Language :: Python :: 3.6
Classifier: Programming Language :: Python :: Implementation :: CPython
Classifier: Programming Language :: Python :: Implementation :: PyPy
Classifier: Topic :: Text Processing :: Linguistic
Requires-Python: >=3.6.0
Requires-Dist: lxml (>=4.2.1)
Requires-Dist: JSON-minify (>=0.3.0)
Requires-Dist: gensim (>=3.4.0)
Requires-Dist: tqdm (>=4.23.3)
Requires-Dist: numpy (<1.18.0,>=1.14.3)
Requires-Dist: termcolor (>=1.1.0)
Requires-Dist: scikit-learn (<0.23.0,>=0.19.1)
Requires-Dist: terminaltables (==3.1.0)
Requires-Dist: torch (<=1.7.1,>=1.3.1)
Requires-Dist: pyyaml (==5.1b3)
Requires-Dist: typing (<4.0)
Requires-Dist: click (<8.0,>=7.0)
